<annotation>
	<folder>indialicenseplate</folder>
	<filename>0005.jpg</filename>
	<path>/home/abhishek/tensorflow4things/training/rawImages/indialicenseplate/0005.jpg</path>
	<source>
		<database>Unknown</database>
	</source>
	<size>
		<width>541</width>
		<height>370</height>
		<depth>3</depth>
	</size>
	<segmented>0</segmented>
	<object>
		<name>inlp</name>
		<pose>Unspecified</pose>
		<truncated>0</truncated>
		<difficult>0</difficult>
		<bndbox>
			<xmin>10</xmin>
			<ymin>70</ymin>
			<xmax>529</xmax>
			<ymax>192</ymax>
		</bndbox>
	</object>
	<object>
		<name>inlp</name>
		<pose>Unspecified</pose>
		<truncated>0</truncated>
		<difficult>0</difficult>
		<bndbox>
			<xmin>2</xmin>
			<ymin>187</ymin>
			<xmax>535</xmax>
			<ymax>328</ymax>
		</bndbox>
	</object>
</annotation>
